{
    "brand": "turbochef",
    "model": "ngc",
    "issues": [
        {
            "name": "Magnetron Is Malfunctioning",
            "idx": 0,
            "url": "https://www.partstown.com/part-predictor/turbochef/ngc/magnetron-is-malfunctioning",
            "results": [
                {
                    "image_src": "https://partstown.sirv.com/products/TBC/TBCNGC-3015.view?thumb&image.rules=G0&w=200",
                    "product_name": "TurboChef NGC-3015 Magnetron Service Kit",
                    "manufacturer_info": "",
                    "info_item_1": "",
                    "info_item_2": "",
                    "info_item_3": "Mfr Part #:\nNGC-3015",
                    "fix_rate": 64.0,
                    "list_price": "$ 155.52"
                },
                {
                    "image_src": "https://partstown.sirv.com/products/TBC/TBCNGC-3062-1.view?thumb&image.rules=G0&w=200",
                    "product_name": "TurboChef NGC-3062-1 Transformer, 208/240 Volt, 60HZ",
                    "manufacturer_info": "",
                    "info_item_1": "",
                    "info_item_2": "",
                    "info_item_3": "Mfr Part #:\nNGC-3062-1",
                    "fix_rate": 26.0,
                    "list_price": "$ 405.70"
                },
                {
                    "image_src": "https://partstown.sirv.com/products/TBC/TBC100481.view?thumb&image.rules=G0&w=200",
                    "product_name": "TurboChef 100481 Diode, High Voltage",
                    "manufacturer_info": "",
                    "info_item_1": "",
                    "info_item_2": "",
                    "info_item_3": "Mfr Part #:\n100481",
                    "fix_rate": 21.0,
                    "list_price": "$ 28.02"
                },
                {
                    "image_src": "https://partstown.sirv.com/products/TBC/TBC100599.view?thumb&image.rules=G0&w=200",
                    "product_name": "TurboChef 100599 Fuse, 20 Amp, ATMR, Individual",
                    "manufacturer_info": "",
                    "info_item_1": "",
                    "info_item_2": "",
                    "info_item_3": "Mfr Part #:\n100599",
                    "fix_rate": 21.0,
                    "list_price": "$ 37.62"
                },
                {
                    "image_src": "https://partstown.sirv.com/products/TBC/TBCNGC-3020.view?thumb&image.rules=G0&w=200",
                    "product_name": "TurboChef NGC-3020 Capacitor Service Upgrade Kit",
                    "manufacturer_info": "",
                    "info_item_1": "",
                    "info_item_2": "",
                    "info_item_3": "Mfr Part #:\nNGC-3020",
                    "fix_rate": 20.0,
                    "list_price": "$ 77.60"
                },
                {
                    "image_src": "https://partstown.sirv.com/products/TBC/TBCNGC-3029.view?thumb&image.rules=G0&w=200",
                    "product_name": "TurboChef NGC-3029 Waveguide Cover Service Kit",
                    "manufacturer_info": "",
                    "info_item_1": "",
                    "info_item_2": "",
                    "info_item_3": "Mfr Part #:\nNGC-3029",
                    "fix_rate": 10.0,
                    "list_price": "$ 508.57"
                }
            ]
        },
        {
            "name": "Fuse Is Blown",
            "idx": 1,
            "url": "https://www.partstown.com/part-predictor/turbochef/ngc/fuse-is-blown",
            "results": [
                {
                    "image_src": "https://partstown.sirv.com/products/TBC/TBC100599.view?thumb&image.rules=G0&w=200",
                    "product_name": "TurboChef 100599 Fuse, 20 Amp, ATMR, Individual",
                    "manufacturer_info": "",
                    "info_item_1": "",
                    "info_item_2": "",
                    "info_item_3": "Mfr Part #:\n100599",
                    "fix_rate": 57.0,
                    "list_price": "$ 37.62"
                },
                {
                    "image_src": "https://partstown.sirv.com/products/TBC/TBCNGC-3062-1.view?thumb&image.rules=G0&w=200",
                    "product_name": "TurboChef NGC-3062-1 Transformer, 208/240 Volt, 60HZ",
                    "manufacturer_info": "",
                    "info_item_1": "",
                    "info_item_2": "",
                    "info_item_3": "Mfr Part #:\nNGC-3062-1",
                    "fix_rate": 29.0,
                    "list_price": "$ 405.70"
                },
                {
                    "image_src": "https://partstown.sirv.com/products/TBC/TBCNGC-3015.view?thumb&image.rules=G0&w=200",
                    "product_name": "TurboChef NGC-3015 Magnetron Service Kit",
                    "manufacturer_info": "",
                    "info_item_1": "",
                    "info_item_2": "",
                    "info_item_3": "Mfr Part #:\nNGC-3015",
                    "fix_rate": 26.0,
                    "list_price": "$ 155.52"
                },
                {
                    "image_src": "https://partstown.sirv.com/products/TBC/TBCNGC-3020.view?thumb&image.rules=G0&w=200",
                    "product_name": "TurboChef NGC-3020 Capacitor Service Upgrade Kit",
                    "manufacturer_info": "",
                    "info_item_1": "",
                    "info_item_2": "",
                    "info_item_3": "Mfr Part #:\nNGC-3020",
                    "fix_rate": 14.0,
                    "list_price": "$ 77.60"
                },
                {
                    "image_src": "https://partstown.sirv.com/products/TBC/TBC101273.view?thumb&image.rules=G0&w=200",
                    "product_name": "TurboChef 101273 Relay 2 Pole",
                    "manufacturer_info": "",
                    "info_item_1": "",
                    "info_item_2": "",
                    "info_item_3": "Mfr Part #:\n101273",
                    "fix_rate": 13.0,
                    "list_price": "$ 54.61"
                },
                {
                    "image_src": "https://partstown.sirv.com/products/TBC/TBC100481.view?thumb&image.rules=G0&w=200",
                    "product_name": "TurboChef 100481 Diode, High Voltage",
                    "manufacturer_info": "",
                    "info_item_1": "",
                    "info_item_2": "",
                    "info_item_3": "Mfr Part #:\n100481",
                    "fix_rate": 13.0,
                    "list_price": "$ 28.02"
                }
            ]
        },
        {
            "name": "Transformer Is Malfunctioning",
            "idx": 2,
            "url": "https://www.partstown.com/part-predictor/turbochef/ngc/transformer-is-malfunctioning",
            "results": [
                {
                    "image_src": "https://partstown.sirv.com/products/TBC/TBCNGC-3062-1.view?thumb&image.rules=G0&w=200",
                    "product_name": "TurboChef NGC-3062-1 Transformer, 208/240 Volt, 60HZ",
                    "manufacturer_info": "",
                    "info_item_1": "",
                    "info_item_2": "",
                    "info_item_3": "Mfr Part #:\nNGC-3062-1",
                    "fix_rate": 81.0,
                    "list_price": "$ 405.70"
                },
                {
                    "image_src": "https://partstown.sirv.com/products/TBC/TBCNGC-3015.view?thumb&image.rules=G0&w=200",
                    "product_name": "TurboChef NGC-3015 Magnetron Service Kit",
                    "manufacturer_info": "",
                    "info_item_1": "",
                    "info_item_2": "",
                    "info_item_3": "Mfr Part #:\nNGC-3015",
                    "fix_rate": 46.0,
                    "list_price": "$ 155.52"
                },
                {
                    "image_src": "https://partstown.sirv.com/products/TBC/TBC100599.view?thumb&image.rules=G0&w=200",
                    "product_name": "TurboChef 100599 Fuse, 20 Amp, ATMR, Individual",
                    "manufacturer_info": "",
                    "info_item_1": "",
                    "info_item_2": "",
                    "info_item_3": "Mfr Part #:\n100599",
                    "fix_rate": 33.0,
                    "list_price": "$ 37.62"
                },
                {
                    "image_src": "https://partstown.sirv.com/products/TBC/TBCNGC-3020.view?thumb&image.rules=G0&w=200",
                    "product_name": "TurboChef NGC-3020 Capacitor Service Upgrade Kit",
                    "manufacturer_info": "",
                    "info_item_1": "",
                    "info_item_2": "",
                    "info_item_3": "Mfr Part #:\nNGC-3020",
                    "fix_rate": 23.0,
                    "list_price": "$ 77.60"
                },
                {
                    "image_src": "https://partstown.sirv.com/products/TBC/TBC100481.view?thumb&image.rules=G0&w=200",
                    "product_name": "TurboChef 100481 Diode, High Voltage",
                    "manufacturer_info": "",
                    "info_item_1": "",
                    "info_item_2": "",
                    "info_item_3": "Mfr Part #:\n100481",
                    "fix_rate": 23.0,
                    "list_price": "$ 28.02"
                }
            ]
        },
        {
            "name": "Door Is Malfunctioning",
            "idx": 3,
            "url": "https://www.partstown.com/part-predictor/turbochef/ngc/door-is-malfunctioning",
            "results": [
                {
                    "image_src": "https://partstown.sirv.com/products/TBC/TBC102012.view?thumb&image.rules=G0&w=200",
                    "product_name": "TurboChef 102012 Switch, Interlock, NGO Oven Primary Switch Only",
                    "manufacturer_info": "",
                    "info_item_1": "",
                    "info_item_2": "",
                    "info_item_3": "Mfr Part #:\n102012",
                    "fix_rate": 26.0,
                    "list_price": "$ 8.00"
                },
                {
                    "image_src": "https://partstown.sirv.com/products/TBC/TBCENC-3050.view?thumb&image.rules=G0&w=200",
                    "product_name": "TurboChef ENC-3050 Door Switch Assembly, Service Kit",
                    "manufacturer_info": "",
                    "info_item_1": "",
                    "info_item_2": "",
                    "info_item_3": "Mfr Part #:\nENC-3050",
                    "fix_rate": 22.0,
                    "list_price": "$ 224.75"
                },
                {
                    "image_src": "https://partstown.sirv.com/products/TBC/TBCNGC-1573.view?thumb&image.rules=G0&w=200",
                    "product_name": "TurboChef NGC-1573 Hinge, Right HHB/NGC",
                    "manufacturer_info": "",
                    "info_item_1": "",
                    "info_item_2": "",
                    "info_item_3": "Mfr Part #:\nNGC-1573",
                    "fix_rate": 19.0,
                    "list_price": "$ 244.42"
                },
                {
                    "image_src": "https://partstown.sirv.com/products/TBC/TBCNGC-1572.view?thumb&image.rules=G0&w=200",
                    "product_name": "TurboChef NGC-1572 Door Hinge and Spring Assembly, LH",
                    "manufacturer_info": "",
                    "info_item_1": "",
                    "info_item_2": "",
                    "info_item_3": "Mfr Part #:\nNGC-1572",
                    "fix_rate": 19.0,
                    "list_price": "$ 241.53"
                }
            ]
        },
        {
            "name": "Door Switch Is Malfunctioning",
            "idx": 4,
            "url": "https://www.partstown.com/part-predictor/turbochef/ngc/door-switch-is-malfunctioning",
            "results": [
                {
                    "image_src": "https://partstown.sirv.com/products/TBC/TBC102012.view?thumb&image.rules=G0&w=200",
                    "product_name": "TurboChef 102012 Switch, Interlock, NGO Oven Primary Switch Only",
                    "manufacturer_info": "",
                    "info_item_1": "",
                    "info_item_2": "",
                    "info_item_3": "Mfr Part #:\n102012",
                    "fix_rate": 47.0,
                    "list_price": "$ 8.00"
                },
                {
                    "image_src": "https://partstown.sirv.com/products/TBC/TBCENC-3050.view?thumb&image.rules=G0&w=200",
                    "product_name": "TurboChef ENC-3050 Door Switch Assembly, Service Kit",
                    "manufacturer_info": "",
                    "info_item_1": "",
                    "info_item_2": "",
                    "info_item_3": "Mfr Part #:\nENC-3050",
                    "fix_rate": 32.0,
                    "list_price": "$ 224.75"
                },
                {
                    "image_src": "https://partstown.sirv.com/products/TBC/TBC100599.view?thumb&image.rules=G0&w=200",
                    "product_name": "TurboChef 100599 Fuse, 20 Amp, ATMR, Individual",
                    "manufacturer_info": "",
                    "info_item_1": "",
                    "info_item_2": "",
                    "info_item_3": "Mfr Part #:\n100599",
                    "fix_rate": 13.0,
                    "list_price": "$ 37.62"
                }
            ]
        },
        {
            "name": "Hi-limit Is Tripping Or Wont Reset",
            "idx": 5,
            "url": "https://www.partstown.com/part-predictor/turbochef/ngc/hi-limit-is-tripping-or-wont-reset",
            "results": [
                {
                    "image_src": "https://partstown.sirv.com/products/TBC/TBC102075.view?thumb&image.rules=G0&w=200",
                    "product_name": "TurboChef 102075 Hi Limit Thermostat EGO 3 Pole",
                    "manufacturer_info": "",
                    "info_item_1": "",
                    "info_item_2": "",
                    "info_item_3": "Mfr Part #:\n102075",
                    "fix_rate": 47.0,
                    "list_price": "$ 170.84"
                },
                {
                    "image_src": "https://partstown.sirv.com/products/TBC/TBCNGC-3005.view?thumb&image.rules=G0&w=200",
                    "product_name": "TurboChef NGC-3005 Solid State Relay, Dual 40A",
                    "manufacturer_info": "",
                    "info_item_1": "",
                    "info_item_2": "",
                    "info_item_3": "Mfr Part #:\nNGC-3005",
                    "fix_rate": 29.0,
                    "list_price": "$ 303.72"
                }
            ]
        },
        {
            "name": "Switch Is Malfunctioning",
            "idx": 6,
            "url": "https://www.partstown.com/part-predictor/turbochef/ngc/switch-is-malfunctioning",
            "results": [
                {
                    "image_src": "https://partstown.sirv.com/products/TBC/TBC102012.view?thumb&image.rules=G0&w=200",
                    "product_name": "TurboChef 102012 Switch, Interlock, NGO Oven Primary Switch Only",
                    "manufacturer_info": "",
                    "info_item_1": "",
                    "info_item_2": "",
                    "info_item_3": "Mfr Part #:\n102012",
                    "fix_rate": 52.0,
                    "list_price": "$ 8.00"
                },
                {
                    "image_src": "https://partstown.sirv.com/products/TBC/TBCENC-3050.view?thumb&image.rules=G0&w=200",
                    "product_name": "TurboChef ENC-3050 Door Switch Assembly, Service Kit",
                    "manufacturer_info": "",
                    "info_item_1": "",
                    "info_item_2": "",
                    "info_item_3": "Mfr Part #:\nENC-3050",
                    "fix_rate": 30.0,
                    "list_price": "$ 224.75"
                }
            ]
        },
        {
            "name": "Hinge Is Defective Or Damaged",
            "idx": 7,
            "url": "https://www.partstown.com/part-predictor/turbochef/ngc/hinge-is-defective-or-damaged",
            "results": [
                {
                    "image_src": "https://partstown.sirv.com/products/TBC/TBCNGC-1573.view?thumb&image.rules=G0&w=200",
                    "product_name": "TurboChef NGC-1573 Hinge, Right HHB/NGC",
                    "manufacturer_info": "",
                    "info_item_1": "",
                    "info_item_2": "",
                    "info_item_3": "Mfr Part #:\nNGC-1573",
                    "fix_rate": 67.0,
                    "list_price": "$ 244.42"
                },
                {
                    "image_src": "https://partstown.sirv.com/products/TBC/TBCNGC-1572.view?thumb&image.rules=G0&w=200",
                    "product_name": "TurboChef NGC-1572 Door Hinge and Spring Assembly, LH",
                    "manufacturer_info": "",
                    "info_item_1": "",
                    "info_item_2": "",
                    "info_item_3": "Mfr Part #:\nNGC-1572",
                    "fix_rate": 62.0,
                    "list_price": "$ 241.53"
                },
                {
                    "image_src": "https://partstown.sirv.com/products/TBC/TBC102012.view?thumb&image.rules=G0&w=200",
                    "product_name": "TurboChef 102012 Switch, Interlock, NGO Oven Primary Switch Only",
                    "manufacturer_info": "",
                    "info_item_1": "",
                    "info_item_2": "",
                    "info_item_3": "Mfr Part #:\n102012",
                    "fix_rate": 16.0,
                    "list_price": "$ 8.00"
                }
            ]
        },
        {
            "name": "Relay Is Malfunctioning",
            "idx": 8,
            "url": "https://www.partstown.com/part-predictor/turbochef/ngc/relay-is-malfunctioning",
            "results": [
                {
                    "image_src": "https://partstown.sirv.com/products/TBC/TBCNGC-3005.view?thumb&image.rules=G0&w=200",
                    "product_name": "TurboChef NGC-3005 Solid State Relay, Dual 40A",
                    "manufacturer_info": "",
                    "info_item_1": "",
                    "info_item_2": "",
                    "info_item_3": "Mfr Part #:\nNGC-3005",
                    "fix_rate": 43.0,
                    "list_price": "$ 303.72"
                },
                {
                    "image_src": "https://partstown.sirv.com/products/TBC/TBC101273.view?thumb&image.rules=G0&w=200",
                    "product_name": "TurboChef 101273 Relay 2 Pole",
                    "manufacturer_info": "",
                    "info_item_1": "",
                    "info_item_2": "",
                    "info_item_3": "Mfr Part #:\n101273",
                    "fix_rate": 35.0,
                    "list_price": "$ 54.61"
                },
                {
                    "image_src": "https://partstown.sirv.com/products/TBC/TBCNGC-3015.view?thumb&image.rules=G0&w=200",
                    "product_name": "TurboChef NGC-3015 Magnetron Service Kit",
                    "manufacturer_info": "",
                    "info_item_1": "",
                    "info_item_2": "",
                    "info_item_3": "Mfr Part #:\nNGC-3015",
                    "fix_rate": 16.0,
                    "list_price": "$ 155.52"
                },
                {
                    "image_src": "https://partstown.sirv.com/products/TBC/TBC102075.view?thumb&image.rules=G0&w=200",
                    "product_name": "TurboChef 102075 Hi Limit Thermostat EGO 3 Pole",
                    "manufacturer_info": "",
                    "info_item_1": "",
                    "info_item_2": "",
                    "info_item_3": "Mfr Part #:\n102075",
                    "fix_rate": 14.0,
                    "list_price": "$ 170.84"
                },
                {
                    "image_src": "https://partstown.sirv.com/products/TBC/TBC100599.view?thumb&image.rules=G0&w=200",
                    "product_name": "TurboChef 100599 Fuse, 20 Amp, ATMR, Individual",
                    "manufacturer_info": "",
                    "info_item_1": "",
                    "info_item_2": "",
                    "info_item_3": "Mfr Part #:\n100599",
                    "fix_rate": 13.0,
                    "list_price": "$ 37.62"
                }
            ]
        },
        {
            "name": "Fan Motor Is Malfunctioning",
            "idx": 9,
            "url": "https://www.partstown.com/part-predictor/turbochef/ngc/fan-motor-is-malfunctioning",
            "results": [
                {
                    "image_src": "https://partstown.sirv.com/products/TBC/TBCNGC-3077.view?thumb&image.rules=G0&w=200",
                    "product_name": "TurboChef NGC-3077 Cooling Fan Service Kit, NGC, 230V",
                    "manufacturer_info": "",
                    "info_item_1": "",
                    "info_item_2": "",
                    "info_item_3": "Mfr Part #:\nNGC-3077",
                    "fix_rate": 41.0,
                    "list_price": "$ 310.90"
                },
                {
                    "image_src": "https://partstown.sirv.com/products/TBC/TBCNGC-3015.view?thumb&image.rules=G0&w=200",
                    "product_name": "TurboChef NGC-3015 Magnetron Service Kit",
                    "manufacturer_info": "",
                    "info_item_1": "",
                    "info_item_2": "",
                    "info_item_3": "Mfr Part #:\nNGC-3015",
                    "fix_rate": 13.0,
                    "list_price": "$ 155.52"
                }
            ]
        },
        {
            "name": "Heating Element Is Malfunctioning",
            "idx": 10,
            "url": "https://www.partstown.com/part-predictor/turbochef/ngc/heating-element-is-malfunctioning",
            "results": [
                {
                    "image_src": "https://partstown.sirv.com/products/TBC/TBCNGC-3003.view?thumb&image.rules=G0&w=200",
                    "product_name": "TurboChef NGC-3003 Element Service Kit, Bottom IR, 3000W, 208V",
                    "manufacturer_info": "",
                    "info_item_1": "",
                    "info_item_2": "",
                    "info_item_3": "Mfr Part #:\nNGC-3003",
                    "fix_rate": 43.0,
                    "list_price": "$ 642.92"
                },
                {
                    "image_src": "https://partstown.sirv.com/products/TBC/TBCNGC-3005.view?thumb&image.rules=G0&w=200",
                    "product_name": "TurboChef NGC-3005 Solid State Relay, Dual 40A",
                    "manufacturer_info": "",
                    "info_item_1": "",
                    "info_item_2": "",
                    "info_item_3": "Mfr Part #:\nNGC-3005",
                    "fix_rate": 22.0,
                    "list_price": "$ 303.72"
                },
                {
                    "image_src": "https://partstown.sirv.com/products/TBC/TBCNGC-3015.view?thumb&image.rules=G0&w=200",
                    "product_name": "TurboChef NGC-3015 Magnetron Service Kit",
                    "manufacturer_info": "",
                    "info_item_1": "",
                    "info_item_2": "",
                    "info_item_3": "Mfr Part #:\nNGC-3015",
                    "fix_rate": 16.0,
                    "list_price": "$ 155.52"
                },
                {
                    "image_src": "https://partstown.sirv.com/products/TBC/TBC102075.view?thumb&image.rules=G0&w=200",
                    "product_name": "TurboChef 102075 Hi Limit Thermostat EGO 3 Pole",
                    "manufacturer_info": "",
                    "info_item_1": "",
                    "info_item_2": "",
                    "info_item_3": "Mfr Part #:\n102075",
                    "fix_rate": 12.0,
                    "list_price": "$ 170.84"
                }
            ]
        },
        {
            "name": "Wiring Issue",
            "idx": 11,
            "url": "https://www.partstown.com/part-predictor/turbochef/ngc/wiring-issue",
            "results": [
                {
                    "image_src": "https://partstown.sirv.com/products/TBC/TBCNGC-3003.view?thumb&image.rules=G0&w=200",
                    "product_name": "TurboChef NGC-3003 Element Service Kit, Bottom IR, 3000W, 208V",
                    "manufacturer_info": "",
                    "info_item_1": "",
                    "info_item_2": "",
                    "info_item_3": "Mfr Part #:\nNGC-3003",
                    "fix_rate": 27.0,
                    "list_price": "$ 642.92"
                },
                {
                    "image_src": "https://partstown.sirv.com/products/TBC/TBCNGC-3015.view?thumb&image.rules=G0&w=200",
                    "product_name": "TurboChef NGC-3015 Magnetron Service Kit",
                    "manufacturer_info": "",
                    "info_item_1": "",
                    "info_item_2": "",
                    "info_item_3": "Mfr Part #:\nNGC-3015",
                    "fix_rate": 17.0,
                    "list_price": "$ 155.52"
                },
                {
                    "image_src": "https://partstown.sirv.com/products/TBC/TBCNGC-3062-1.view?thumb&image.rules=G0&w=200",
                    "product_name": "TurboChef NGC-3062-1 Transformer, 208/240 Volt, 60HZ",
                    "manufacturer_info": "",
                    "info_item_1": "",
                    "info_item_2": "",
                    "info_item_3": "Mfr Part #:\nNGC-3062-1",
                    "fix_rate": 15.0,
                    "list_price": "$ 405.70"
                },
                {
                    "image_src": "https://partstown.sirv.com/products/TBC/TBCNGC-3005.view?thumb&image.rules=G0&w=200",
                    "product_name": "TurboChef NGC-3005 Solid State Relay, Dual 40A",
                    "manufacturer_info": "",
                    "info_item_1": "",
                    "info_item_2": "",
                    "info_item_3": "Mfr Part #:\nNGC-3005",
                    "fix_rate": 12.0,
                    "list_price": "$ 303.72"
                },
                {
                    "image_src": "https://partstown.sirv.com/products/TBC/TBC102075.view?thumb&image.rules=G0&w=200",
                    "product_name": "TurboChef 102075 Hi Limit Thermostat EGO 3 Pole",
                    "manufacturer_info": "",
                    "info_item_1": "",
                    "info_item_2": "",
                    "info_item_3": "Mfr Part #:\n102075",
                    "fix_rate": 11.0,
                    "list_price": "$ 170.84"
                },
                {
                    "image_src": "https://partstown.sirv.com/products/TBC/TBC100599.view?thumb&image.rules=G0&w=200",
                    "product_name": "TurboChef 100599 Fuse, 20 Amp, ATMR, Individual",
                    "manufacturer_info": "",
                    "info_item_1": "",
                    "info_item_2": "",
                    "info_item_3": "Mfr Part #:\n100599",
                    "fix_rate": 11.0,
                    "list_price": "$ 37.62"
                }
            ]
        },
        {
            "name": "Unit Is Overheating",
            "idx": 12,
            "url": "https://www.partstown.com/part-predictor/turbochef/ngc/unit-is-overheating",
            "results": [
                {
                    "image_src": "https://partstown.sirv.com/products/TBC/TBCNGC-3062-1.view?thumb&image.rules=G0&w=200",
                    "product_name": "TurboChef NGC-3062-1 Transformer, 208/240 Volt, 60HZ",
                    "manufacturer_info": "",
                    "info_item_1": "",
                    "info_item_2": "",
                    "info_item_3": "Mfr Part #:\nNGC-3062-1",
                    "fix_rate": 29.0,
                    "list_price": "$ 405.70"
                },
                {
                    "image_src": "https://partstown.sirv.com/products/TBC/TBCNGC-3015.view?thumb&image.rules=G0&w=200",
                    "product_name": "TurboChef NGC-3015 Magnetron Service Kit",
                    "manufacturer_info": "",
                    "info_item_1": "",
                    "info_item_2": "",
                    "info_item_3": "Mfr Part #:\nNGC-3015",
                    "fix_rate": 19.0,
                    "list_price": "$ 155.52"
                },
                {
                    "image_src": "https://partstown.sirv.com/products/TBC/TBCNGC-3005.view?thumb&image.rules=G0&w=200",
                    "product_name": "TurboChef NGC-3005 Solid State Relay, Dual 40A",
                    "manufacturer_info": "",
                    "info_item_1": "",
                    "info_item_2": "",
                    "info_item_3": "Mfr Part #:\nNGC-3005",
                    "fix_rate": 16.0,
                    "list_price": "$ 303.72"
                },
                {
                    "image_src": "https://partstown.sirv.com/products/TBC/TBC100481.view?thumb&image.rules=G0&w=200",
                    "product_name": "TurboChef 100481 Diode, High Voltage",
                    "manufacturer_info": "",
                    "info_item_1": "",
                    "info_item_2": "",
                    "info_item_3": "Mfr Part #:\n100481",
                    "fix_rate": 14.0,
                    "list_price": "$ 28.02"
                },
                {
                    "image_src": "https://partstown.sirv.com/products/TBC/TBC102075.view?thumb&image.rules=G0&w=200",
                    "product_name": "TurboChef 102075 Hi Limit Thermostat EGO 3 Pole",
                    "manufacturer_info": "",
                    "info_item_1": "",
                    "info_item_2": "",
                    "info_item_3": "Mfr Part #:\n102075",
                    "fix_rate": 13.0,
                    "list_price": "$ 170.84"
                },
                {
                    "image_src": "https://partstown.sirv.com/products/TBC/TBCNGC-3020.view?thumb&image.rules=G0&w=200",
                    "product_name": "TurboChef NGC-3020 Capacitor Service Upgrade Kit",
                    "manufacturer_info": "",
                    "info_item_1": "",
                    "info_item_2": "",
                    "info_item_3": "Mfr Part #:\nNGC-3020",
                    "fix_rate": 10.0,
                    "list_price": "$ 77.60"
                },
                {
                    "image_src": "https://partstown.sirv.com/products/TBC/TBC100599.view?thumb&image.rules=G0&w=200",
                    "product_name": "TurboChef 100599 Fuse, 20 Amp, ATMR, Individual",
                    "manufacturer_info": "",
                    "info_item_1": "",
                    "info_item_2": "",
                    "info_item_3": "Mfr Part #:\n100599",
                    "fix_rate": 10.0,
                    "list_price": "$ 37.62"
                }
            ]
        },
        {
            "name": "Wave Guide Is Malfunctioning",
            "idx": 13,
            "url": "https://www.partstown.com/part-predictor/turbochef/ngc/wave-guide-is-malfunctioning",
            "results": [
                {
                    "image_src": "https://partstown.sirv.com/products/TBC/TBCNGC-3015.view?thumb&image.rules=G0&w=200",
                    "product_name": "TurboChef NGC-3015 Magnetron Service Kit",
                    "manufacturer_info": "",
                    "info_item_1": "",
                    "info_item_2": "",
                    "info_item_3": "Mfr Part #:\nNGC-3015",
                    "fix_rate": 69.0,
                    "list_price": "$ 155.52"
                },
                {
                    "image_src": "https://partstown.sirv.com/products/TBC/TBCNGC-3029.view?thumb&image.rules=G0&w=200",
                    "product_name": "TurboChef NGC-3029 Waveguide Cover Service Kit",
                    "manufacturer_info": "",
                    "info_item_1": "",
                    "info_item_2": "",
                    "info_item_3": "Mfr Part #:\nNGC-3029",
                    "fix_rate": 49.0,
                    "list_price": "$ 508.57"
                },
                {
                    "image_src": "https://partstown.sirv.com/products/TBC/TBCNGC-3016.view?thumb&image.rules=G0&w=200",
                    "product_name": "TurboChef NGC-3016 Waveguide, Front, with Gasket",
                    "manufacturer_info": "",
                    "info_item_1": "",
                    "info_item_2": "",
                    "info_item_3": "Mfr Part #:\nNGC-3016",
                    "fix_rate": 45.0,
                    "list_price": "$ 304.18"
                },
                {
                    "image_src": "https://partstown.sirv.com/products/TBC/TBCNGC-3017.view?thumb&image.rules=G0&w=200",
                    "product_name": "TurboChef NGC-3017 Rear Waveguide and Gasket Assembly",
                    "manufacturer_info": "",
                    "info_item_1": "",
                    "info_item_2": "",
                    "info_item_3": "Mfr Part #:\nNGC-3017",
                    "fix_rate": 42.0,
                    "list_price": "$ 301.77"
                },
                {
                    "image_src": "https://partstown.sirv.com/products/TBC/TBC100481.view?thumb&image.rules=G0&w=200",
                    "product_name": "TurboChef 100481 Diode, High Voltage",
                    "manufacturer_info": "",
                    "info_item_1": "",
                    "info_item_2": "",
                    "info_item_3": "Mfr Part #:\n100481",
                    "fix_rate": 24.0,
                    "list_price": "$ 28.02"
                },
                {
                    "image_src": "https://partstown.sirv.com/products/TBC/TBCNGC-3020.view?thumb&image.rules=G0&w=200",
                    "product_name": "TurboChef NGC-3020 Capacitor Service Upgrade Kit",
                    "manufacturer_info": "",
                    "info_item_1": "",
                    "info_item_2": "",
                    "info_item_3": "Mfr Part #:\nNGC-3020",
                    "fix_rate": 22.0,
                    "list_price": "$ 77.60"
                },
                {
                    "image_src": "https://partstown.sirv.com/products/TBC/TBCNGC-3062-1.view?thumb&image.rules=G0&w=200",
                    "product_name": "TurboChef NGC-3062-1 Transformer, 208/240 Volt, 60HZ",
                    "manufacturer_info": "",
                    "info_item_1": "",
                    "info_item_2": "",
                    "info_item_3": "Mfr Part #:\nNGC-3062-1",
                    "fix_rate": 21.0,
                    "list_price": "$ 405.70"
                },
                {
                    "image_src": "https://partstown.sirv.com/products/TBC/TBC101273.view?thumb&image.rules=G0&w=200",
                    "product_name": "TurboChef 101273 Relay 2 Pole",
                    "manufacturer_info": "",
                    "info_item_1": "",
                    "info_item_2": "",
                    "info_item_3": "Mfr Part #:\n101273",
                    "fix_rate": 12.0,
                    "list_price": "$ 54.61"
                },
                {
                    "image_src": "https://partstown.sirv.com/products/TBC/TBC100599.view?thumb&image.rules=G0&w=200",
                    "product_name": "TurboChef 100599 Fuse, 20 Amp, ATMR, Individual",
                    "manufacturer_info": "",
                    "info_item_1": "",
                    "info_item_2": "",
                    "info_item_3": "Mfr Part #:\n100599",
                    "fix_rate": 12.0,
                    "list_price": "$ 37.62"
                }
            ]
        },
        {
            "name": "Capacitor Is Malfunctioning",
            "idx": 14,
            "url": "https://www.partstown.com/part-predictor/turbochef/ngc/capacitor-is-malfunctioning",
            "results": [
                {
                    "image_src": "https://partstown.sirv.com/products/TBC/TBCNGC-3020.view?thumb&image.rules=G0&w=200",
                    "product_name": "TurboChef NGC-3020 Capacitor Service Upgrade Kit",
                    "manufacturer_info": "",
                    "info_item_1": "",
                    "info_item_2": "",
                    "info_item_3": "Mfr Part #:\nNGC-3020",
                    "fix_rate": 74.0,
                    "list_price": "$ 77.60"
                },
                {
                    "image_src": "https://partstown.sirv.com/products/TBC/TBCNGC-3015.view?thumb&image.rules=G0&w=200",
                    "product_name": "TurboChef NGC-3015 Magnetron Service Kit",
                    "manufacturer_info": "",
                    "info_item_1": "",
                    "info_item_2": "",
                    "info_item_3": "Mfr Part #:\nNGC-3015",
                    "fix_rate": 50.0,
                    "list_price": "$ 155.52"
                },
                {
                    "image_src": "https://partstown.sirv.com/products/TBC/TBC100481.view?thumb&image.rules=G0&w=200",
                    "product_name": "TurboChef 100481 Diode, High Voltage",
                    "manufacturer_info": "",
                    "info_item_1": "",
                    "info_item_2": "",
                    "info_item_3": "Mfr Part #:\n100481",
                    "fix_rate": 43.0,
                    "list_price": "$ 28.02"
                },
                {
                    "image_src": "https://partstown.sirv.com/products/TBC/TBCNGC-3062-1.view?thumb&image.rules=G0&w=200",
                    "product_name": "TurboChef NGC-3062-1 Transformer, 208/240 Volt, 60HZ",
                    "manufacturer_info": "",
                    "info_item_1": "",
                    "info_item_2": "",
                    "info_item_3": "Mfr Part #:\nNGC-3062-1",
                    "fix_rate": 29.0,
                    "list_price": "$ 405.70"
                },
                {
                    "image_src": "https://partstown.sirv.com/products/TBC/TBC100599.view?thumb&image.rules=G0&w=200",
                    "product_name": "TurboChef 100599 Fuse, 20 Amp, ATMR, Individual",
                    "manufacturer_info": "",
                    "info_item_1": "",
                    "info_item_2": "",
                    "info_item_3": "Mfr Part #:\n100599",
                    "fix_rate": 19.0,
                    "list_price": "$ 37.62"
                }
            ]
        },
        {
            "name": "Blower Motor Is Malfunctioning",
            "idx": 15,
            "url": "https://www.partstown.com/part-predictor/turbochef/ngc/blower-motor-is-malfunctioning",
            "results": [
                {
                    "image_src": "https://partstown.sirv.com/products/TBC/TBCNGC-1025.view?thumb&image.rules=G0&w=200",
                    "product_name": "TurboChef NGC-1025 Blower Assembly, NGC",
                    "manufacturer_info": "",
                    "info_item_1": "",
                    "info_item_2": "",
                    "info_item_3": "Mfr Part #:\nNGC-1025",
                    "fix_rate": 32.0,
                    "list_price": "$ 1,493.20"
                }
            ]
        },
        {
            "name": "Keypad Is Not Responding Or Damaged",
            "idx": 16,
            "url": "https://www.partstown.com/part-predictor/turbochef/ngc/keypad-is-not-responding-or-damaged",
            "results": [
                {
                    "image_src": "https://partstown.sirv.com/products/TBC/TBCNGC-1110-1.view?thumb&image.rules=G0&w=200",
                    "product_name": "TurboChef NGC-1110-1 Control Panel Overlay, Generic",
                    "manufacturer_info": "",
                    "info_item_1": "",
                    "info_item_2": "",
                    "info_item_3": "Mfr Part #:\nNGC-1110-1",
                    "fix_rate": 36.0,
                    "list_price": "$ 134.50"
                },
                {
                    "image_src": "https://partstown.sirv.com/products/TBC/TBCNGC-1495-1.view?thumb&image.rules=G0&w=200",
                    "product_name": "TurboChef NGC-1495-1 Keypad, General Market, Ngc/Tornado 2",
                    "manufacturer_info": "",
                    "info_item_1": "",
                    "info_item_2": "",
                    "info_item_3": "Mfr Part #:\nNGC-1495-1",
                    "fix_rate": 19.0,
                    "list_price": "$ 92.89"
                },
                {
                    "image_src": "https://partstown.sirv.com/products/TBC/TBCNGC-1495-2.view?thumb&image.rules=G0&w=200",
                    "product_name": "TurboChef NGC-1495-2 Keypad, NGC/Tornado 2, Subway",
                    "manufacturer_info": "",
                    "info_item_1": "",
                    "info_item_2": "",
                    "info_item_3": "Mfr Part #:\nNGC-1495-2",
                    "fix_rate": 17.0,
                    "list_price": "$ 89.67"
                }
            ]
        },
        {
            "name": "Diode Is Malfunctioning",
            "idx": 17,
            "url": "https://www.partstown.com/part-predictor/turbochef/ngc/diode-is-malfunctioning",
            "results": [
                {
                    "image_src": "https://partstown.sirv.com/products/TBC/TBC100481.view?thumb&image.rules=G0&w=200",
                    "product_name": "TurboChef 100481 Diode, High Voltage",
                    "manufacturer_info": "",
                    "info_item_1": "",
                    "info_item_2": "",
                    "info_item_3": "Mfr Part #:\n100481",
                    "fix_rate": 86.0,
                    "list_price": "$ 28.02"
                },
                {
                    "image_src": "https://partstown.sirv.com/products/TBC/TBCNGC-3015.view?thumb&image.rules=G0&w=200",
                    "product_name": "TurboChef NGC-3015 Magnetron Service Kit",
                    "manufacturer_info": "",
                    "info_item_1": "",
                    "info_item_2": "",
                    "info_item_3": "Mfr Part #:\nNGC-3015",
                    "fix_rate": 67.0,
                    "list_price": "$ 155.52"
                },
                {
                    "image_src": "https://partstown.sirv.com/products/TBC/TBCNGC-3020.view?thumb&image.rules=G0&w=200",
                    "product_name": "TurboChef NGC-3020 Capacitor Service Upgrade Kit",
                    "manufacturer_info": "",
                    "info_item_1": "",
                    "info_item_2": "",
                    "info_item_3": "Mfr Part #:\nNGC-3020",
                    "fix_rate": 37.0,
                    "list_price": "$ 77.60"
                },
                {
                    "image_src": "https://partstown.sirv.com/products/TBC/TBCNGC-3062-1.view?thumb&image.rules=G0&w=200",
                    "product_name": "TurboChef NGC-3062-1 Transformer, 208/240 Volt, 60HZ",
                    "manufacturer_info": "",
                    "info_item_1": "",
                    "info_item_2": "",
                    "info_item_3": "Mfr Part #:\nNGC-3062-1",
                    "fix_rate": 30.0,
                    "list_price": "$ 405.70"
                },
                {
                    "image_src": "https://partstown.sirv.com/products/TBC/TBC100599.view?thumb&image.rules=G0&w=200",
                    "product_name": "TurboChef 100599 Fuse, 20 Amp, ATMR, Individual",
                    "manufacturer_info": "",
                    "info_item_1": "",
                    "info_item_2": "",
                    "info_item_3": "Mfr Part #:\n100599",
                    "fix_rate": 22.0,
                    "list_price": "$ 37.62"
                }
            ]
        },
        {
            "name": "Controller Is Malfunctioning",
            "idx": 18,
            "url": "https://www.partstown.com/part-predictor/turbochef/ngc/controller-is-malfunctioning",
            "results": [
                {
                    "image_src": "https://partstown.sirv.com/products/TBC/TBCCON-3007-12-21.view?thumb&image.rules=G0&w=200",
                    "product_name": "TurboChef CON-3007-12-21 Control Board Service Kit, NGC",
                    "manufacturer_info": "",
                    "info_item_1": "",
                    "info_item_2": "",
                    "info_item_3": "Mfr Part #:\nCON-3007-12-21",
                    "fix_rate": 25.0,
                    "list_price": "$ 882.77"
                },
                {
                    "image_src": "https://partstown.sirv.com/products/TBC/TBCCON-3007-6-116.view?thumb&image.rules=G0&w=200",
                    "product_name": "TurboChef CON-3007-6-116 Control Board Service Kit, NGC",
                    "manufacturer_info": "",
                    "info_item_1": "",
                    "info_item_2": "",
                    "info_item_3": "Mfr Part #:\nCON-3007-6-116",
                    "fix_rate": 11.0,
                    "list_price": "$ 882.77"
                }
            ]
        },
        {
            "name": "Cooling Fan Is Malfunctioning",
            "idx": 19,
            "url": "https://www.partstown.com/part-predictor/turbochef/ngc/cooling-fan-is-malfunctioning",
            "results": [
                {
                    "image_src": "https://partstown.sirv.com/products/TBC/TBCNGC-3077.view?thumb&image.rules=G0&w=200",
                    "product_name": "TurboChef NGC-3077 Cooling Fan Service Kit, NGC, 230V",
                    "manufacturer_info": "",
                    "info_item_1": "",
                    "info_item_2": "",
                    "info_item_3": "Mfr Part #:\nNGC-3077",
                    "fix_rate": 61.0,
                    "list_price": "$ 310.90"
                },
                {
                    "image_src": "https://partstown.sirv.com/products/TBC/TBC100481.view?thumb&image.rules=G0&w=200",
                    "product_name": "TurboChef 100481 Diode, High Voltage",
                    "manufacturer_info": "",
                    "info_item_1": "",
                    "info_item_2": "",
                    "info_item_3": "Mfr Part #:\n100481",
                    "fix_rate": 13.0,
                    "list_price": "$ 28.02"
                },
                {
                    "image_src": "https://partstown.sirv.com/products/TBC/TBCNGC-3015.view?thumb&image.rules=G0&w=200",
                    "product_name": "TurboChef NGC-3015 Magnetron Service Kit",
                    "manufacturer_info": "",
                    "info_item_1": "",
                    "info_item_2": "",
                    "info_item_3": "Mfr Part #:\nNGC-3015",
                    "fix_rate": 11.0,
                    "list_price": "$ 155.52"
                },
                {
                    "image_src": "https://partstown.sirv.com/products/TBC/TBC100599.view?thumb&image.rules=G0&w=200",
                    "product_name": "TurboChef 100599 Fuse, 20 Amp, ATMR, Individual",
                    "manufacturer_info": "",
                    "info_item_1": "",
                    "info_item_2": "",
                    "info_item_3": "Mfr Part #:\n100599",
                    "fix_rate": 11.0,
                    "list_price": "$ 37.62"
                }
            ]
        },
        {
            "name": "Unit Is Not Reaching Set Temperature",
            "idx": 20,
            "url": "https://www.partstown.com/part-predictor/turbochef/ngc/unit-is-not-reaching-set-temperature",
            "results": [
                {
                    "image_src": "https://partstown.sirv.com/products/TBC/TBCNGC-3015.view?thumb&image.rules=G0&w=200",
                    "product_name": "TurboChef NGC-3015 Magnetron Service Kit",
                    "manufacturer_info": "",
                    "info_item_1": "",
                    "info_item_2": "",
                    "info_item_3": "Mfr Part #:\nNGC-3015",
                    "fix_rate": 15.0,
                    "list_price": "$ 155.52"
                },
                {
                    "image_src": "https://partstown.sirv.com/products/TBC/TBCNGC-3005.view?thumb&image.rules=G0&w=200",
                    "product_name": "TurboChef NGC-3005 Solid State Relay, Dual 40A",
                    "manufacturer_info": "",
                    "info_item_1": "",
                    "info_item_2": "",
                    "info_item_3": "Mfr Part #:\nNGC-3005",
                    "fix_rate": 11.0,
                    "list_price": "$ 303.72"
                },
                {
                    "image_src": "https://partstown.sirv.com/products/TBC/TBCNGC-3003.view?thumb&image.rules=G0&w=200",
                    "product_name": "TurboChef NGC-3003 Element Service Kit, Bottom IR, 3000W, 208V",
                    "manufacturer_info": "",
                    "info_item_1": "",
                    "info_item_2": "",
                    "info_item_3": "Mfr Part #:\nNGC-3003",
                    "fix_rate": 11.0,
                    "list_price": "$ 642.92"
                }
            ]
        },
        {
            "name": "Display Is Malfunctioning",
            "idx": 21,
            "url": "https://www.partstown.com/part-predictor/turbochef/ngc/display-is-malfunctioning",
            "results": [
                {
                    "image_src": "https://partstown.sirv.com/products/TBC/TBCNGC-3023.view?thumb&image.rules=G0&w=200",
                    "product_name": "TurboChef NGC-3023 VF Display Service Kit with Cable",
                    "manufacturer_info": "",
                    "info_item_1": "",
                    "info_item_2": "",
                    "info_item_3": "Mfr Part #:\nNGC-3023",
                    "fix_rate": 35.0,
                    "list_price": "$ 814.86"
                },
                {
                    "image_src": "https://partstown.sirv.com/products/TBC/TBCNGC-3069.view?thumb&image.rules=G0&w=200",
                    "product_name": "TurboChef NGC-3069 Power Supply Service Kit with Bracket",
                    "manufacturer_info": "",
                    "info_item_1": "",
                    "info_item_2": "",
                    "info_item_3": "Mfr Part #:\nNGC-3069",
                    "fix_rate": 14.0,
                    "list_price": "$ 209.32"
                }
            ]
        },
        {
            "name": "I/o Control Board Is Malfunctioning",
            "idx": 22,
            "url": "https://www.partstown.com/part-predictor/turbochef/ngc/i-o-control-board-is-malfunctioning",
            "results": [
                {
                    "image_src": "https://partstown.sirv.com/products/TBC/TBCCON-3007-1-1.view?thumb&image.rules=G0&w=200",
                    "product_name": "TurboChef CON-3007-1-1 Control Board Service Kit, I/O, General Market",
                    "manufacturer_info": "",
                    "info_item_1": "",
                    "info_item_2": "",
                    "info_item_3": "Mfr Part #:\nCON-3007-1-1",
                    "fix_rate": 19.0,
                    "list_price": "$ 882.77"
                }
            ]
        },
        {
            "name": "Wave Guide Cover Is Defective",
            "idx": 23,
            "url": "https://www.partstown.com/part-predictor/turbochef/ngc/wave-guide-cover-is-defective",
            "results": [
                {
                    "image_src": "https://partstown.sirv.com/products/TBC/TBCNGC-3029.view?thumb&image.rules=G0&w=200",
                    "product_name": "TurboChef NGC-3029 Waveguide Cover Service Kit",
                    "manufacturer_info": "",
                    "info_item_1": "",
                    "info_item_2": "",
                    "info_item_3": "Mfr Part #:\nNGC-3029",
                    "fix_rate": 73.0,
                    "list_price": "$ 508.57"
                },
                {
                    "image_src": "https://partstown.sirv.com/products/TBC/TBCNGC-3015.view?thumb&image.rules=G0&w=200",
                    "product_name": "TurboChef NGC-3015 Magnetron Service Kit",
                    "manufacturer_info": "",
                    "info_item_1": "",
                    "info_item_2": "",
                    "info_item_3": "Mfr Part #:\nNGC-3015",
                    "fix_rate": 50.0,
                    "list_price": "$ 155.52"
                },
                {
                    "image_src": "https://partstown.sirv.com/products/TBC/TBCNGC-3017.view?thumb&image.rules=G0&w=200",
                    "product_name": "TurboChef NGC-3017 Rear Waveguide and Gasket Assembly",
                    "manufacturer_info": "",
                    "info_item_1": "",
                    "info_item_2": "",
                    "info_item_3": "Mfr Part #:\nNGC-3017",
                    "fix_rate": 37.0,
                    "list_price": "$ 301.77"
                },
                {
                    "image_src": "https://partstown.sirv.com/products/TBC/TBCNGC-3016.view?thumb&image.rules=G0&w=200",
                    "product_name": "TurboChef NGC-3016 Waveguide, Front, with Gasket",
                    "manufacturer_info": "",
                    "info_item_1": "",
                    "info_item_2": "",
                    "info_item_3": "Mfr Part #:\nNGC-3016",
                    "fix_rate": 33.0,
                    "list_price": "$ 304.18"
                },
                {
                    "image_src": "https://partstown.sirv.com/products/TBC/TBC100481.view?thumb&image.rules=G0&w=200",
                    "product_name": "TurboChef 100481 Diode, High Voltage",
                    "manufacturer_info": "",
                    "info_item_1": "",
                    "info_item_2": "",
                    "info_item_3": "Mfr Part #:\n100481",
                    "fix_rate": 23.0,
                    "list_price": "$ 28.02"
                },
                {
                    "image_src": "https://partstown.sirv.com/products/TBC/TBCNGC-3020.view?thumb&image.rules=G0&w=200",
                    "product_name": "TurboChef NGC-3020 Capacitor Service Upgrade Kit",
                    "manufacturer_info": "",
                    "info_item_1": "",
                    "info_item_2": "",
                    "info_item_3": "Mfr Part #:\nNGC-3020",
                    "fix_rate": 17.0,
                    "list_price": "$ 77.60"
                }
            ]
        },
        {
            "name": "Smoke Coming From Unit",
            "idx": 24,
            "url": "https://www.partstown.com/part-predictor/turbochef/ngc/smoke-coming-from-unit",
            "results": [
                {
                    "image_src": "https://partstown.sirv.com/products/TBC/TBCNGC-3062-1.view?thumb&image.rules=G0&w=200",
                    "product_name": "TurboChef NGC-3062-1 Transformer, 208/240 Volt, 60HZ",
                    "manufacturer_info": "",
                    "info_item_1": "",
                    "info_item_2": "",
                    "info_item_3": "Mfr Part #:\nNGC-3062-1",
                    "fix_rate": 75.0,
                    "list_price": "$ 405.70"
                },
                {
                    "image_src": "https://partstown.sirv.com/products/TBC/TBCNGC-3015.view?thumb&image.rules=G0&w=200",
                    "product_name": "TurboChef NGC-3015 Magnetron Service Kit",
                    "manufacturer_info": "",
                    "info_item_1": "",
                    "info_item_2": "",
                    "info_item_3": "Mfr Part #:\nNGC-3015",
                    "fix_rate": 36.0,
                    "list_price": "$ 155.52"
                },
                {
                    "image_src": "https://partstown.sirv.com/products/TBC/TBC100481.view?thumb&image.rules=G0&w=200",
                    "product_name": "TurboChef 100481 Diode, High Voltage",
                    "manufacturer_info": "",
                    "info_item_1": "",
                    "info_item_2": "",
                    "info_item_3": "Mfr Part #:\n100481",
                    "fix_rate": 32.0,
                    "list_price": "$ 28.02"
                },
                {
                    "image_src": "https://partstown.sirv.com/products/TBC/TBC100599.view?thumb&image.rules=G0&w=200",
                    "product_name": "TurboChef 100599 Fuse, 20 Amp, ATMR, Individual",
                    "manufacturer_info": "",
                    "info_item_1": "",
                    "info_item_2": "",
                    "info_item_3": "Mfr Part #:\n100599",
                    "fix_rate": 32.0,
                    "list_price": "$ 37.62"
                },
                {
                    "image_src": "https://partstown.sirv.com/products/TBC/TBCNGC-3020.view?thumb&image.rules=G0&w=200",
                    "product_name": "TurboChef NGC-3020 Capacitor Service Upgrade Kit",
                    "manufacturer_info": "",
                    "info_item_1": "",
                    "info_item_2": "",
                    "info_item_3": "Mfr Part #:\nNGC-3020",
                    "fix_rate": 25.0,
                    "list_price": "$ 77.60"
                }
            ]
        },
        {
            "name": "Heating Element Is Not Heating Properly",
            "idx": 25,
            "url": "https://www.partstown.com/part-predictor/turbochef/ngc/heating-element-is-not-heating-properly",
            "results": [
                {
                    "image_src": "https://partstown.sirv.com/products/TBC/TBCNGC-3003.view?thumb&image.rules=G0&w=200",
                    "product_name": "TurboChef NGC-3003 Element Service Kit, Bottom IR, 3000W, 208V",
                    "manufacturer_info": "",
                    "info_item_1": "",
                    "info_item_2": "",
                    "info_item_3": "Mfr Part #:\nNGC-3003",
                    "fix_rate": 48.0,
                    "list_price": "$ 642.92"
                },
                {
                    "image_src": "https://partstown.sirv.com/products/TBC/TBCNGC-3005.view?thumb&image.rules=G0&w=200",
                    "product_name": "TurboChef NGC-3005 Solid State Relay, Dual 40A",
                    "manufacturer_info": "",
                    "info_item_1": "",
                    "info_item_2": "",
                    "info_item_3": "Mfr Part #:\nNGC-3005",
                    "fix_rate": 30.0,
                    "list_price": "$ 303.72"
                }
            ]
        },
        {
            "name": "Motor Is Malfunctioning",
            "idx": 26,
            "url": "https://www.partstown.com/part-predictor/turbochef/ngc/motor-is-malfunctioning",
            "results": [
                {
                    "image_src": "https://partstown.sirv.com/products/TBC/TBCNGC-1025.view?thumb&image.rules=G0&w=200",
                    "product_name": "TurboChef NGC-1025 Blower Assembly, NGC",
                    "manufacturer_info": "",
                    "info_item_1": "",
                    "info_item_2": "",
                    "info_item_3": "Mfr Part #:\nNGC-1025",
                    "fix_rate": 30.0,
                    "list_price": "$ 1,493.20"
                }
            ]
        },
        {
            "name": "Breaker Is Tripping Or Wont Reset",
            "idx": 27,
            "url": "https://www.partstown.com/part-predictor/turbochef/ngc/breaker-is-tripping-or-wont-reset",
            "results": [
                {
                    "image_src": "https://partstown.sirv.com/products/TBC/TBC100599.view?thumb&image.rules=G0&w=200",
                    "product_name": "TurboChef 100599 Fuse, 20 Amp, ATMR, Individual",
                    "manufacturer_info": "",
                    "info_item_1": "",
                    "info_item_2": "",
                    "info_item_3": "Mfr Part #:\n100599",
                    "fix_rate": 19.0,
                    "list_price": "$ 37.62"
                }
            ]
        },
        {
            "name": "Unit Is Making Noise",
            "idx": 28,
            "url": "https://www.partstown.com/part-predictor/turbochef/ngc/unit-is-making-noise",
            "results": [
                {
                    "image_src": "https://partstown.sirv.com/products/TBC/TBCNGC-3077.view?thumb&image.rules=G0&w=200",
                    "product_name": "TurboChef NGC-3077 Cooling Fan Service Kit, NGC, 230V",
                    "manufacturer_info": "",
                    "info_item_1": "",
                    "info_item_2": "",
                    "info_item_3": "Mfr Part #:\nNGC-3077",
                    "fix_rate": 27.0,
                    "list_price": "$ 310.90"
                },
                {
                    "image_src": "https://partstown.sirv.com/products/TBC/TBCNGC-1025.view?thumb&image.rules=G0&w=200",
                    "product_name": "TurboChef NGC-1025 Blower Assembly, NGC",
                    "manufacturer_info": "",
                    "info_item_1": "",
                    "info_item_2": "",
                    "info_item_3": "Mfr Part #:\nNGC-1025",
                    "fix_rate": 19.0,
                    "list_price": "$ 1,493.20"
                }
            ]
        },
        {
            "name": "Latch Is Damaged Or Not Latching",
            "idx": 29,
            "url": "https://www.partstown.com/part-predictor/turbochef/ngc/latch-is-damaged-or-not-latching",
            "results": [
                {
                    "image_src": "https://partstown.sirv.com/products/TBC/TBCENC-3050.view?thumb&image.rules=G0&w=200",
                    "product_name": "TurboChef ENC-3050 Door Switch Assembly, Service Kit",
                    "manufacturer_info": "",
                    "info_item_1": "",
                    "info_item_2": "",
                    "info_item_3": "Mfr Part #:\nENC-3050",
                    "fix_rate": 42.0,
                    "list_price": "$ 224.75"
                },
                {
                    "image_src": "https://partstown.sirv.com/products/TBC/TBC102012.view?thumb&image.rules=G0&w=200",
                    "product_name": "TurboChef 102012 Switch, Interlock, NGO Oven Primary Switch Only",
                    "manufacturer_info": "",
                    "info_item_1": "",
                    "info_item_2": "",
                    "info_item_3": "Mfr Part #:\n102012",
                    "fix_rate": 25.0,
                    "list_price": "$ 8.00"
                }
            ]
        },
        {
            "name": "Fuse Holder Is Malfunctioning",
            "idx": 30,
            "url": "https://www.partstown.com/part-predictor/turbochef/ngc/fuse-holder-is-malfunctioning",
            "results": [
                {
                    "image_src": "https://partstown.sirv.com/products/TBC/TBC100586.view?thumb&image.rules=G0&w=200",
                    "product_name": "TurboChef 100586 Fuse Holder",
                    "manufacturer_info": "",
                    "info_item_1": "",
                    "info_item_2": "",
                    "info_item_3": "Mfr Part #:\n100586",
                    "fix_rate": 57.0,
                    "list_price": "$ 12.55"
                },
                {
                    "image_src": "https://partstown.sirv.com/products/TBC/TBCNGC-3015.view?thumb&image.rules=G0&w=200",
                    "product_name": "TurboChef NGC-3015 Magnetron Service Kit",
                    "manufacturer_info": "",
                    "info_item_1": "",
                    "info_item_2": "",
                    "info_item_3": "Mfr Part #:\nNGC-3015",
                    "fix_rate": 26.0,
                    "list_price": "$ 155.52"
                },
                {
                    "image_src": "https://partstown.sirv.com/products/TBC/TBC100599.view?thumb&image.rules=G0&w=200",
                    "product_name": "TurboChef 100599 Fuse, 20 Amp, ATMR, Individual",
                    "manufacturer_info": "",
                    "info_item_1": "",
                    "info_item_2": "",
                    "info_item_3": "Mfr Part #:\n100599",
                    "fix_rate": 26.0,
                    "list_price": "$ 37.62"
                }
            ]
        },
        {
            "name": "Sensor Is Malfunctioning",
            "idx": 31,
            "url": "https://www.partstown.com/part-predictor/turbochef/ngc/sensor-is-malfunctioning",
            "results": [
                {
                    "image_src": "https://partstown.sirv.com/products/TBC/TBCENC-3050.view?thumb&image.rules=G0&w=200",
                    "product_name": "TurboChef ENC-3050 Door Switch Assembly, Service Kit",
                    "manufacturer_info": "",
                    "info_item_1": "",
                    "info_item_2": "",
                    "info_item_3": "Mfr Part #:\nENC-3050",
                    "fix_rate": 30.0,
                    "list_price": "$ 224.75"
                },
                {
                    "image_src": "https://partstown.sirv.com/products/TBC/TBC102012.view?thumb&image.rules=G0&w=200",
                    "product_name": "TurboChef 102012 Switch, Interlock, NGO Oven Primary Switch Only",
                    "manufacturer_info": "",
                    "info_item_1": "",
                    "info_item_2": "",
                    "info_item_3": "Mfr Part #:\n102012",
                    "fix_rate": 30.0,
                    "list_price": "$ 8.00"
                }
            ]
        },
        {
            "name": "Fire Coming Out Of Unit",
            "idx": 32,
            "url": "https://www.partstown.com/part-predictor/turbochef/ngc/fire-coming-out-of-unit",
            "results": [
                {
                    "image_src": "https://partstown.sirv.com/products/TBC/TBCNGC-3015.view?thumb&image.rules=G0&w=200",
                    "product_name": "TurboChef NGC-3015 Magnetron Service Kit",
                    "manufacturer_info": "",
                    "info_item_1": "",
                    "info_item_2": "",
                    "info_item_3": "Mfr Part #:\nNGC-3015",
                    "fix_rate": 42.0,
                    "list_price": "$ 155.52"
                },
                {
                    "image_src": "https://partstown.sirv.com/products/TBC/TBCNGC-3062-1.view?thumb&image.rules=G0&w=200",
                    "product_name": "TurboChef NGC-3062-1 Transformer, 208/240 Volt, 60HZ",
                    "manufacturer_info": "",
                    "info_item_1": "",
                    "info_item_2": "",
                    "info_item_3": "Mfr Part #:\nNGC-3062-1",
                    "fix_rate": 42.0,
                    "list_price": "$ 405.70"
                },
                {
                    "image_src": "https://partstown.sirv.com/products/TBC/TBCNGC-3020.view?thumb&image.rules=G0&w=200",
                    "product_name": "TurboChef NGC-3020 Capacitor Service Upgrade Kit",
                    "manufacturer_info": "",
                    "info_item_1": "",
                    "info_item_2": "",
                    "info_item_3": "Mfr Part #:\nNGC-3020",
                    "fix_rate": 26.0,
                    "list_price": "$ 77.60"
                },
                {
                    "image_src": "https://partstown.sirv.com/products/TBC/TBC100481.view?thumb&image.rules=G0&w=200",
                    "product_name": "TurboChef 100481 Diode, High Voltage",
                    "manufacturer_info": "",
                    "info_item_1": "",
                    "info_item_2": "",
                    "info_item_3": "Mfr Part #:\n100481",
                    "fix_rate": 26.0,
                    "list_price": "$ 28.02"
                }
            ]
        },
        {
            "name": "Thermocouple Is Malfunctioning",
            "idx": 33,
            "url": "https://www.partstown.com/part-predictor/turbochef/ngc/thermocouple-is-malfunctioning",
            "results": [
                {
                    "image_src": "https://partstown.sirv.com/products/TBC/TBCNGC-1140.view?thumb&image.rules=G0&w=200",
                    "product_name": "TurboChef NGC-1140 Thermocouple Assembly, Cook Cavity",
                    "manufacturer_info": "",
                    "info_item_1": "",
                    "info_item_2": "",
                    "info_item_3": "Mfr Part #:\nNGC-1140",
                    "fix_rate": 63.0,
                    "list_price": "$ 169.50"
                }
            ]
        },
        {
            "name": "Display Is Blank",
            "idx": 34,
            "url": "https://www.partstown.com/part-predictor/turbochef/ngc/display-is-blank",
            "results": [
                {
                    "image_src": "https://partstown.sirv.com/products/TBC/TBCNGC-3023.view?thumb&image.rules=G0&w=200",
                    "product_name": "TurboChef NGC-3023 VF Display Service Kit with Cable",
                    "manufacturer_info": "",
                    "info_item_1": "",
                    "info_item_2": "",
                    "info_item_3": "Mfr Part #:\nNGC-3023",
                    "fix_rate": 50.0,
                    "list_price": "$ 814.86"
                }
            ]
        },
        {
            "name": "Spring Is Malfunctioning",
            "idx": 35,
            "url": "https://www.partstown.com/part-predictor/turbochef/ngc/spring-is-malfunctioning",
            "results": [
                {
                    "image_src": "https://partstown.sirv.com/products/TBC/TBCENC-3050.view?thumb&image.rules=G0&w=200",
                    "product_name": "TurboChef ENC-3050 Door Switch Assembly, Service Kit",
                    "manufacturer_info": "",
                    "info_item_1": "",
                    "info_item_2": "",
                    "info_item_3": "Mfr Part #:\nENC-3050",
                    "fix_rate": 78.0,
                    "list_price": "$ 224.75"
                }
            ]
        },
        {
            "name": "Connector Is Faulty",
            "idx": 36,
            "url": "https://www.partstown.com/part-predictor/turbochef/ngc/connector-is-faulty",
            "results": [
                {
                    "image_src": "https://partstown.sirv.com/products/TBC/TBCNGC-3015.view?thumb&image.rules=G0&w=200",
                    "product_name": "TurboChef NGC-3015 Magnetron Service Kit",
                    "manufacturer_info": "",
                    "info_item_1": "",
                    "info_item_2": "",
                    "info_item_3": "Mfr Part #:\nNGC-3015",
                    "fix_rate": 29.0,
                    "list_price": "$ 155.52"
                }
            ]
        },
        {
            "name": "Unit Making Noise",
            "idx": 37,
            "url": "https://www.partstown.com/part-predictor/turbochef/ngc/unit-making-noise",
            "results": [
                {
                    "image_src": "https://partstown.sirv.com/products/TBC/TBCNGC-3015.view?thumb&image.rules=G0&w=200",
                    "product_name": "TurboChef NGC-3015 Magnetron Service Kit",
                    "manufacturer_info": "",
                    "info_item_1": "",
                    "info_item_2": "",
                    "info_item_3": "Mfr Part #:\nNGC-3015",
                    "fix_rate": 29.0,
                    "list_price": "$ 155.52"
                }
            ]
        },
        {
            "name": "Fan Motor Is Making Noise",
            "idx": 38,
            "url": "https://www.partstown.com/part-predictor/turbochef/ngc/fan-motor-is-making-noise",
            "results": [
                {
                    "image_src": "https://partstown.sirv.com/products/TBC/TBCNGC-3077.view?thumb&image.rules=G0&w=200",
                    "product_name": "TurboChef NGC-3077 Cooling Fan Service Kit, NGC, 230V",
                    "manufacturer_info": "",
                    "info_item_1": "",
                    "info_item_2": "",
                    "info_item_3": "Mfr Part #:\nNGC-3077",
                    "fix_rate": 56.0,
                    "list_price": "$ 310.90"
                }
            ]
        },
        {
            "name": "Wave Guide Cover Is Malfunctioning",
            "idx": 39,
            "url": "https://www.partstown.com/part-predictor/turbochef/ngc/wave-guide-cover-is-malfunctioning",
            "results": [
                {
                    "image_src": "https://partstown.sirv.com/products/TBC/TBCNGC-3029.view?thumb&image.rules=G0&w=200",
                    "product_name": "TurboChef NGC-3029 Waveguide Cover Service Kit",
                    "manufacturer_info": "",
                    "info_item_1": "",
                    "info_item_2": "",
                    "info_item_3": "Mfr Part #:\nNGC-3029",
                    "fix_rate": 87.0,
                    "list_price": "$ 508.57"
                },
                {
                    "image_src": "https://partstown.sirv.com/products/TBC/TBCNGC-3015.view?thumb&image.rules=G0&w=200",
                    "product_name": "TurboChef NGC-3015 Magnetron Service Kit",
                    "manufacturer_info": "",
                    "info_item_1": "",
                    "info_item_2": "",
                    "info_item_3": "Mfr Part #:\nNGC-3015",
                    "fix_rate": 53.0,
                    "list_price": "$ 155.52"
                },
                {
                    "image_src": "https://partstown.sirv.com/products/TBC/TBCNGC-3017.view?thumb&image.rules=G0&w=200",
                    "product_name": "TurboChef NGC-3017 Rear Waveguide and Gasket Assembly",
                    "manufacturer_info": "",
                    "info_item_1": "",
                    "info_item_2": "",
                    "info_item_3": "Mfr Part #:\nNGC-3017",
                    "fix_rate": 47.0,
                    "list_price": "$ 301.77"
                },
                {
                    "image_src": "https://partstown.sirv.com/products/TBC/TBCNGC-3016.view?thumb&image.rules=G0&w=200",
                    "product_name": "TurboChef NGC-3016 Waveguide, Front, with Gasket",
                    "manufacturer_info": "",
                    "info_item_1": "",
                    "info_item_2": "",
                    "info_item_3": "Mfr Part #:\nNGC-3016",
                    "fix_rate": 33.0,
                    "list_price": "$ 304.18"
                }
            ]
        },
        {
            "name": "Thermostat Is Malfunctioning",
            "idx": 40,
            "url": "https://www.partstown.com/part-predictor/turbochef/ngc/thermostat-is-malfunctioning",
            "results": [
                {
                    "image_src": "https://partstown.sirv.com/products/TBC/TBC102075.view?thumb&image.rules=G0&w=200",
                    "product_name": "TurboChef 102075 Hi Limit Thermostat EGO 3 Pole",
                    "manufacturer_info": "",
                    "info_item_1": "",
                    "info_item_2": "",
                    "info_item_3": "Mfr Part #:\n102075",
                    "fix_rate": 46.0,
                    "list_price": "$ 170.84"
                }
            ]
        },
        {
            "name": "Probe Is Malfunctioning",
            "idx": 41,
            "url": "https://www.partstown.com/part-predictor/turbochef/ngc/probe-is-malfunctioning",
            "results": [
                {
                    "image_src": "https://partstown.sirv.com/products/TBC/TBCNGC-1140.view?thumb&image.rules=G0&w=200",
                    "product_name": "TurboChef NGC-1140 Thermocouple Assembly, Cook Cavity",
                    "manufacturer_info": "",
                    "info_item_1": "",
                    "info_item_2": "",
                    "info_item_3": "Mfr Part #:\nNGC-1140",
                    "fix_rate": 42.0,
                    "list_price": "$ 169.50"
                }
            ]
        },
        {
            "name": "Actuator Is Malfunctioning",
            "idx": 42,
            "url": "https://www.partstown.com/part-predictor/turbochef/ngc/actuator-is-malfunctioning",
            "results": [
                {
                    "image_src": "https://partstown.sirv.com/products/TBC/TBCENC-3050.view?thumb&image.rules=G0&w=200",
                    "product_name": "TurboChef ENC-3050 Door Switch Assembly, Service Kit",
                    "manufacturer_info": "",
                    "info_item_1": "",
                    "info_item_2": "",
                    "info_item_3": "Mfr Part #:\nENC-3050",
                    "fix_rate": 56.0,
                    "list_price": "$ 224.75"
                }
            ]
        },
        {
            "name": "Door Gasket Is Defective",
            "idx": 43,
            "url": "https://www.partstown.com/part-predictor/turbochef/ngc/door-gasket-is-defective",
            "results": [
                {
                    "image_src": "https://partstown.sirv.com/products/TBC/TBCNGC-3021.view?thumb&image.rules=G0&w=200",
                    "product_name": "TurboChef NGC-3021 Door Shunt Service Kit, Ngc",
                    "manufacturer_info": "",
                    "info_item_1": "",
                    "info_item_2": "",
                    "info_item_3": "Mfr Part #:\nNGC-3021",
                    "fix_rate": 56.0,
                    "list_price": "$ 511.14"
                }
            ]
        },
        {
            "name": "Filter Is Malfunctioning",
            "idx": 44,
            "url": "https://www.partstown.com/part-predictor/turbochef/ngc/filter-is-malfunctioning",
            "results": [
                {
                    "image_src": "https://partstown.sirv.com/products/TBC/TBC105406.view?thumb&image.rules=G0&w=200",
                    "product_name": "TurboChef 105406 Filter, EMI, 1PH, 30A, Low Leakage, Replaces 10054",
                    "manufacturer_info": "",
                    "info_item_1": "",
                    "info_item_2": "",
                    "info_item_3": "Mfr Part #:\n105406",
                    "fix_rate": 71.0,
                    "list_price": "$ 72.00"
                }
            ]
        },
        {
            "name": "Interlock Switch Is Malfunctioning",
            "idx": 45,
            "url": "https://www.partstown.com/part-predictor/turbochef/ngc/interlock-switch-is-malfunctioning",
            "results": [
                {
                    "image_src": "https://partstown.sirv.com/products/TBC/TBC102012.view?thumb&image.rules=G0&w=200",
                    "product_name": "TurboChef 102012 Switch, Interlock, NGO Oven Primary Switch Only",
                    "manufacturer_info": "",
                    "info_item_1": "",
                    "info_item_2": "",
                    "info_item_3": "Mfr Part #:\n102012",
                    "fix_rate": 86.0,
                    "list_price": "$ 8.00"
                }
            ]
        },
        {
            "name": "Filter Is Damaged",
            "idx": 46,
            "url": "https://www.partstown.com/part-predictor/turbochef/ngc/filter-is-damaged",
            "results": [
                {
                    "image_src": "https://partstown.sirv.com/products/TBC/TBC105406.view?thumb&image.rules=G0&w=200",
                    "product_name": "TurboChef 105406 Filter, EMI, 1PH, 30A, Low Leakage, Replaces 10054",
                    "manufacturer_info": "",
                    "info_item_1": "",
                    "info_item_2": "",
                    "info_item_3": "Mfr Part #:\n105406",
                    "fix_rate": 83.0,
                    "list_price": "$ 72.00"
                }
            ]
        },
        {
            "name": "Blower Motor Is Making Noise",
            "idx": 47,
            "url": "https://www.partstown.com/part-predictor/turbochef/ngc/blower-motor-is-making-noise",
            "results": [
                {
                    "image_src": "https://partstown.sirv.com/products/TBC/TBCNGC-1025.view?thumb&image.rules=G0&w=200",
                    "product_name": "TurboChef NGC-1025 Blower Assembly, NGC",
                    "manufacturer_info": "",
                    "info_item_1": "",
                    "info_item_2": "",
                    "info_item_3": "Mfr Part #:\nNGC-1025",
                    "fix_rate": 98.0,
                    "list_price": "$ 1,493.20"
                }
            ]
        }
    ]
}