{
    "brand": "wells",
    "model": "f556",
    "issues": [
        {
            "name": "Thermostat Is Malfunctioning",
            "idx": 0,
            "url": "https://www.partstown.com/part-predictor/wells/f556/thermostat-is-malfunctioning",
            "results": []
        },
        {
            "name": "Hi-limit Is Tripping Or Wont Reset",
            "idx": 1,
            "url": "https://www.partstown.com/part-predictor/wells/f556/hi-limit-is-tripping-or-wont-reset",
            "results": []
        }
    ]
}