{
    "brand": "garland",
    "model": "u36-6s",
    "issues": [
        {
            "name": "Burner Is Malfunctioning Or Damaged",
            "idx": 0,
            "url": "https://www.partstown.com/part-predictor/garland/u36-6s/burner-is-malfunctioning-or-damaged",
            "results": [
                {
                    "image_src": "https://partstown.sirv.com/products/GL/GL4524670.view?thumb&image.rules=G0&w=200",
                    "product_name": "Garland 4524670 Knob Kit, Open Burner",
                    "manufacturer_info": "",
                    "info_item_1": "",
                    "info_item_2": "",
                    "info_item_3": "Mfr Part #:\n4524670",
                    "fix_rate": 35.0,
                    "list_price": "$ 47.91"
                },
                {
                    "image_src": "https://partstown.sirv.com/products/GL/GL4530671.view?thumb&image.rules=G0&w=200",
                    "product_name": "Garland 4530671 Burner Valve without Hood, Open Top",
                    "manufacturer_info": "",
                    "info_item_1": "",
                    "info_item_2": "",
                    "info_item_3": "Mfr Part #:\n4530671",
                    "fix_rate": 35.0,
                    "list_price": "$ 47.13"
                }
            ]
        }
    ]
}