{
    "brand": "turbochef",
    "model": "c3-c",
    "issues": [
        {
            "name": "Magnetron Is Malfunctioning",
            "idx": 0,
            "url": "https://www.partstown.com/part-predictor/turbochef/c3-c/magnetron-is-malfunctioning",
            "results": [
                {
                    "image_src": "https://partstown.sirv.com/products/TBC/TBCTC3-3233.view?thumb&image.rules=G0&w=200",
                    "product_name": "TurboChef TC3-3233 Magnetron Service Kit, C3",
                    "manufacturer_info": "",
                    "info_item_1": "",
                    "info_item_2": "",
                    "info_item_3": "Mfr Part #:\nTC3-3233",
                    "fix_rate": 53.0,
                    "list_price": "$ 1,179.16"
                }
            ]
        }
    ]
}