[
    {
        "name": "APWF-15C",
        "parsed_name": "apwf-15c"
    },
    {
        "name": "AT EXPRESS",
        "parsed_name": "at-express"
    },
    {
        "name": "AT-10",
        "parsed_name": "at-10"
    },
    {
        "name": "AT-30",
        "parsed_name": "at-30"
    },
    {
        "name": "BM-80D",
        "parsed_name": "bm-80d"
    },
    {
        "name": "BT-15",
        "parsed_name": "bt-15"
    },
    {
        "name": "CMW-48",
        "parsed_name": "cmw-48"
    },
    {
        "name": "ECO 4000-350L",
        "parsed_name": "eco-4000-350l"
    },
    {
        "name": "ECO-4000-350L",
        "parsed_name": "eco-4000-350l"
    },
    {
        "name": "EF-30NT",
        "parsed_name": "ef-30nt"
    },
    {
        "name": "EG-48S",
        "parsed_name": "eg-48s"
    },
    {
        "name": "FD-36H",
        "parsed_name": "fd-36h"
    },
    {
        "name": "FD-48H",
        "parsed_name": "fd-48h"
    },
    {
        "name": "FD-60H",
        "parsed_name": "fd-60h"
    },
    {
        "name": "FDC-60H",
        "parsed_name": "fdc-60h"
    },
    {
        "name": "GCB-18",
        "parsed_name": "gcb-18"
    },
    {
        "name": "GCB-24",
        "parsed_name": "gcb-24"
    },
    {
        "name": "GCB-36",
        "parsed_name": "gcb-36"
    },
    {
        "name": "GCB-48",
        "parsed_name": "gcb-48"
    },
    {
        "name": "HFW-12D",
        "parsed_name": "hfw-12d"
    },
    {
        "name": "HFW-1D",
        "parsed_name": "hfw-1d"
    },
    {
        "name": "HL-12",
        "parsed_name": "hl-12"
    },
    {
        "name": "HRS-50",
        "parsed_name": "hrs-50"
    },
    {
        "name": "HRSDI-50",
        "parsed_name": "hrsdi-50"
    },
    {
        "name": "M-95-2",
        "parsed_name": "m-95-2"
    },
    {
        "name": "M-95-3",
        "parsed_name": "m-95-3"
    },
    {
        "name": "PD-1A",
        "parsed_name": "pd-1a"
    },
    {
        "name": "RTR-4",
        "parsed_name": "rtr-4"
    },
    {
        "name": "SM-50-11D",
        "parsed_name": "sm-50-11d"
    },
    {
        "name": "SM-50-4D UL",
        "parsed_name": "sm-50-4d-ul"
    },
    {
        "name": "SM-50-7D UL",
        "parsed_name": "sm-50-7d-ul"
    },
    {
        "name": "SPTU-50",
        "parsed_name": "sptu-50"
    },
    {
        "name": "TBTGDL",
        "parsed_name": "tbtgdl"
    },
    {
        "name": "TM-12LD",
        "parsed_name": "tm-12ld"
    },
    {
        "name": "TM-90D",
        "parsed_name": "tm-90d"
    },
    {
        "name": "W-3Vi",
        "parsed_name": "w-3vi"
    },
    {
        "name": "XPRS",
        "parsed_name": "xprs"
    },
    {
        "name": "XTRM-1",
        "parsed_name": "xtrm-1"
    }
]