[
    {
        "name": "Fan Motor Is Malfunctioning",
        "parsed_name": "fan-motor-is-malfunctioning"
    },
    {
        "name": "Pilot Is Malfunctioning",
        "parsed_name": "pilot-is-malfunctioning"
    },
    {
        "name": "Door Switch Is Malfunctioning",
        "parsed_name": "door-switch-is-malfunctioning"
    },
    {
        "name": "Hinge Is Defective Or Damaged",
        "parsed_name": "hinge-is-defective-or-damaged"
    },
    {
        "name": "Door Is Malfunctioning",
        "parsed_name": "door-is-malfunctioning"
    },
    {
        "name": "Blower Motor Is Malfunctioning",
        "parsed_name": "blower-motor-is-malfunctioning"
    },
    {
        "name": "Switch Is Malfunctioning",
        "parsed_name": "switch-is-malfunctioning"
    },
    {
        "name": "Motor Is Malfunctioning",
        "parsed_name": "motor-is-malfunctioning"
    },
    {
        "name": "Thermostat Is Malfunctioning",
        "parsed_name": "thermostat-is-malfunctioning"
    }
]